{
  "type": "Feature",
  "stac_version": "1.1.0",
  "stac_extensions": [
    "https://stac-extensions.github.io/ssys/v1.1.0/schema.json"
  ],
  "id": "13498",
  "geometry": {
    "type": "Polygon",
    "coordinates": [
      [
        [
          6.465222348916768,
          -36.35119726339792
        ],
        [
          6.493027098774348,
          -36.34339144455532
        ],
        [
          6.47302816775948,
          -36.32339251354051
        ],
        [
          6.465222348916768,
          -36.35119726339792
        ],
        [
          6.428954799743508,
          -36.32215649942981
        ],
        [
          6.432573759977231,
          -36.29301551810147
        ],
        [
          6.346520453249695,
          -36.26840658851199
        ],
        [
          6.333982147947609,
          -36.16762132981751
        ],
        [
          6.409468090792529,
          -36.135807885547194
        ],
        [
          6.471157443700235,
          -36.09955147163623
        ],
        [
          6.568980722634024,
          -36.08738062998856
        ],
        [
          6.589391658352326,
          -36.135807885547194
        ],
        [
          6.728738330245221,
          -36.156096333380844
        ],
        [
          6.749828516961372,
          -36.18243122862032
        ],
        [
          6.829144990022826,
          -36.135807885547194
        ],
        [
          6.791440992018181,
          -36.22946657639682
        ],
        [
          6.606807208523378,
          -36.206505665621364
        ],
        [
          6.617708630273796,
          -36.294184720638555
        ],
        [
          6.612040781784572,
          -36.339794754846025
        ],
        [
          6.615002761545043,
          -36.363635351339724
        ],
        [
          6.589391658352326,
          -36.38414650441848
        ],
        [
          6.568880505273796,
          -36.4097576076112
        ],
        [
          6.545039908779984,
          -36.40679562785061
        ],
        [
          6.483317150085497,
          -36.41446782354615
        ],
        [
          6.465222348916768,
          -36.35119726339792
        ]
      ]
    ]
  },
  "bbox": [
    6.333982147947609,
    -36.41446782354615,
    6.829144990022826,
    -36.08738062998856
  ],
  "properties": {
    "grid_code": 255,
    "Shape_Leng": 1.587106,
    "Shape_Area": 0.075853,
    "ssys:targets": [
      "mars"
    ],
    "ssys:local_time": null,
    "ssys:target_class": "planet",
    "instruments": [
      "crism",
      "omega"
    ],
    "platform": "mro/mex",
    "gsd": 0.3,
    "datetime": "2013-04-24T00:00:00Z"
  },
  "links": [
    {
      "rel": "root",
      "href": "../../../catalog.json",
      "type": "application/json"
    },
    {
      "rel": "collection",
      "href": "../collection.json",
      "type": "application/json",
      "title": "hyd_global_290615"
    },
    {
      "rel": "parent",
      "href": "../collection.json",
      "type": "application/json",
      "title": "hyd_global_290615"
    }
  ],
  "assets": {},
  "collection": "ias_hyd_global_290615"
}