{
  "type": "Feature",
  "stac_version": "1.1.0",
  "stac_extensions": [
    "https://stac-extensions.github.io/ssys/v1.1.0/schema.json"
  ],
  "id": "1839",
  "geometry": {
    "type": "Polygon",
    "coordinates": [
      [
        [
          74.53819840364889,
          21.413911060433293
        ],
        [
          74.50031624144816,
          21.446537378848404
        ],
        [
          74.52893386545037,
          21.471190849486902
        ],
        [
          74.46029610889411,
          21.50181838832674
        ],
        [
          74.57320766818708,
          21.492748717217808
        ],
        [
          74.59436466647674,
          21.562989951539407
        ],
        [
          74.60661345496015,
          21.573546180159724
        ],
        [
          74.61443040906494,
          21.545741430302144
        ],
        [
          74.63440706955538,
          21.56574036131707
        ],
        [
          74.60661345496015,
          21.573546180159724
        ],
        [
          74.61984214652239,
          21.595031668685976
        ],
        [
          74.66362599771946,
          21.581396540051287
        ],
        [
          74.7293240450399,
          21.601863152080966
        ],
        [
          74.69464883836946,
          21.517212888398035
        ],
        [
          74.66090899372864,
          21.496434489025035
        ],
        [
          74.64353798460667,
          21.468217734464076
        ],
        [
          74.55256289196132,
          21.437211596707584
        ],
        [
          74.53819840364889,
          21.413911060433293
        ]
      ]
    ]
  },
  "bbox": [
    74.46029610889411,
    21.413911060433293,
    74.7293240450399,
    21.601863152080966
  ],
  "properties": {
    "grid_code": 255,
    "Shape_Leng": 0.879376,
    "Shape_Area": 0.017536,
    "ssys:targets": [
      "mars"
    ],
    "ssys:local_time": "",
    "ssys:target_class": "planet",
    "instruments": [
      "crism",
      "omega"
    ],
    "platform": "mro/mex",
    "gsd": 0.3,
    "datetime": "2013-04-24T00:00:00Z"
  },
  "links": [
    {
      "rel": "root",
      "href": "../../../catalog.json",
      "type": "application/json"
    },
    {
      "rel": "collection",
      "href": "../collection.json",
      "type": "application/json",
      "title": "hyd_global_290615"
    },
    {
      "rel": "parent",
      "href": "../collection.json",
      "type": "application/json",
      "title": "hyd_global_290615"
    }
  ],
  "assets": {},
  "collection": "ias_hyd_global_290615"
}