{
  "type": "Feature",
  "stac_version": "1.1.0",
  "stac_extensions": [
    "https://stac-extensions.github.io/ssys/v1.1.1/schema.json"
  ],
  "id": "8397",
  "geometry": {
    "type": "MultiPolygon",
    "coordinates": [
      [
        [
          [
            92.38221785766845,
            44.1236148040145,
            0.0
          ],
          [
            92.38391969572329,
            44.13893134650761,
            0.0
          ],
          [
            92.38349423620961,
            44.16275707927498,
            0.0
          ],
          [
            92.38349423620961,
            44.17892454079561,
            0.0
          ],
          [
            92.37881418155898,
            44.19126286669298,
            0.0
          ],
          [
            92.37285774836714,
            44.19764475939849,
            0.0
          ],
          [
            92.36732677468898,
            44.1908374071793,
            0.0
          ],
          [
            92.36817769371645,
            44.17892454079562,
            0.0
          ],
          [
            92.37115591031232,
            44.16360799830226,
            0.0
          ],
          [
            92.37583596496313,
            44.12106204693231,
            0.0
          ],
          [
            92.38221785766845,
            44.1236148040145,
            0.0
          ]
        ]
      ]
    ]
  },
  "bbox": [
    92.36732677468898,
    44.12106204693231,
    92.38391969572329,
    44.19764475939849
  ],
  "properties": {
    "Name": "0",
    "description": null,
    "begin": null,
    "end": null,
    "altitudeMode": null,
    "tessellate": -1,
    "extrude": 0,
    "visibility": -1,
    "ssys:targets": [
      "mars"
    ],
    "ssys:local_time": "",
    "ssys:target_class": "planet",
    "instruments": [
      "hirise"
    ],
    "platform": "mro",
    "datetime": "2011-05-11T00:00:00Z"
  },
  "links": [
    {
      "rel": "root",
      "href": "../../../catalog.json",
      "type": "application/json"
    },
    {
      "rel": "collection",
      "href": "../collection.json",
      "type": "application/json",
      "title": "scalloped_depression"
    },
    {
      "rel": "parent",
      "href": "../collection.json",
      "type": "application/json",
      "title": "scalloped_depression"
    }
  ],
  "assets": {},
  "collection": "ias_scalloped_depression"
}