{
  "type": "Feature",
  "stac_version": "1.1.0",
  "stac_extensions": [
    "https://stac-extensions.github.io/ssys/v1.1.0/schema.json"
  ],
  "id": "5106",
  "geometry": {
    "type": "MultiPolygon",
    "coordinates": [
      [
        [
          [
            86.26997043615722,
            42.31554877398065,
            0.0
          ],
          [
            86.26523356269661,
            42.3119961188852,
            0.0
          ],
          [
            86.26925990513807,
            42.31057505684703,
            0.0
          ],
          [
            86.27139149819537,
            42.30844346378979,
            0.0
          ],
          [
            86.27210202921445,
            42.3051276523675,
            0.0
          ],
          [
            86.2747073096176,
            42.30394343400241,
            0.0
          ],
          [
            86.2811020887894,
            42.30133815359903,
            0.0
          ],
          [
            86.27991787042423,
            42.30299605931027,
            0.0
          ],
          [
            86.27470730961758,
            42.30702240175157,
            0.0
          ],
          [
            86.27281256023353,
            42.30868030746279,
            0.0
          ],
          [
            86.26997043615722,
            42.31554877398065,
            0.0
          ]
        ]
      ]
    ]
  },
  "bbox": [
    86.26523356269661,
    42.30133815359903,
    86.2811020887894,
    42.31554877398065
  ],
  "properties": {
    "Name": "0",
    "description": null,
    "begin": null,
    "end": null,
    "altitudeMode": null,
    "tessellate": -1,
    "extrude": 0,
    "visibility": -1,
    "ssys:targets": [
      "mars"
    ],
    "ssys:local_time": null,
    "ssys:target_class": "planet",
    "instruments": [
      "hirise"
    ],
    "platform": "mro",
    "datetime": "2011-05-11T00:00:00Z"
  },
  "links": [
    {
      "rel": "root",
      "href": "../../../catalog.json",
      "type": "application/json"
    },
    {
      "rel": "collection",
      "href": "../collection.json",
      "type": "application/json",
      "title": "scalloped_depression"
    },
    {
      "rel": "parent",
      "href": "../collection.json",
      "type": "application/json",
      "title": "scalloped_depression"
    }
  ],
  "assets": {},
  "collection": "ias_scalloped_depression"
}