{
  "type": "Feature",
  "stac_version": "1.1.0",
  "stac_extensions": [
    "https://stac-extensions.github.io/ssys/v1.1.1/schema.json"
  ],
  "id": "12119",
  "geometry": {
    "type": "Polygon",
    "coordinates": [
      [
        [
          -73.69441277080955,
          -30.44469783352332
        ],
        [
          -73.70955672747999,
          -30.437036773090085
        ],
        [
          -73.72487884834658,
          -30.406748859749143
        ],
        [
          -73.78739221066132,
          -30.38870973489162
        ],
        [
          -73.74475529147662,
          -30.367140731898473
        ],
        [
          -73.7571599736317,
          -30.341741198688737
        ],
        [
          -73.72461160205239,
          -30.27740165336371
        ],
        [
          -73.6665746151653,
          -30.297010850199456
        ],
        [
          -73.68901216861457,
          -30.342966077537028
        ],
        [
          -73.65222126211512,
          -30.38927763326683
        ],
        [
          -73.6867517103762,
          -30.406748859749143
        ],
        [
          -73.69441277080955,
          -30.44469783352332
        ]
      ]
    ]
  },
  "bbox": [
    -73.78739221066132,
    -30.44469783352332,
    -73.65222126211512,
    -30.27740165336371
  ],
  "properties": {
    "grid_code": 255,
    "Shape_Leng": 0.513092,
    "Shape_Area": 0.010258,
    "ssys:targets": [
      "mars"
    ],
    "ssys:local_time": "",
    "ssys:target_class": "planet",
    "instruments": [
      "crism",
      "omega"
    ],
    "platform": "mro/mex",
    "gsd": 0.3,
    "datetime": "2013-04-24T00:00:00Z"
  },
  "links": [
    {
      "rel": "root",
      "href": "../../../catalog.json",
      "type": "application/json"
    },
    {
      "rel": "collection",
      "href": "../collection.json",
      "type": "application/json",
      "title": "hyd_global_290615"
    },
    {
      "rel": "parent",
      "href": "../collection.json",
      "type": "application/json",
      "title": "hyd_global_290615"
    }
  ],
  "assets": {},
  "collection": "ias_hyd_global_290615"
}