{
  "type": "Feature",
  "stac_version": "1.1.0",
  "stac_extensions": [
    "https://stac-extensions.github.io/ssys/v1.1.1/schema.json"
  ],
  "id": "2427",
  "geometry": {
    "type": "MultiPolygon",
    "coordinates": [
      [
        [
          [
            91.05737869515389,
            44.36099068554599,
            0.0
          ],
          [
            91.05562222753223,
            44.36099068554598,
            0.0
          ],
          [
            91.05489036602326,
            44.36025882403698,
            0.0
          ],
          [
            91.05584178598507,
            44.359453776377,
            0.0
          ],
          [
            91.05825692896472,
            44.35923421792433,
            0.0
          ],
          [
            91.05737869515389,
            44.36099068554599,
            0.0
          ]
        ]
      ]
    ]
  },
  "bbox": [
    91.05489036602326,
    44.35923421792433,
    91.05825692896472,
    44.36099068554599
  ],
  "properties": {
    "Name": "0",
    "description": null,
    "begin": null,
    "end": null,
    "altitudeMode": null,
    "tessellate": -1,
    "extrude": 0,
    "visibility": -1,
    "ssys:targets": [
      "mars"
    ],
    "ssys:local_time": "",
    "ssys:target_class": "planet",
    "instruments": [
      "hirise"
    ],
    "platform": "mro",
    "datetime": "2011-05-11T00:00:00Z"
  },
  "links": [
    {
      "rel": "root",
      "href": "../../../catalog.json",
      "type": "application/json"
    },
    {
      "rel": "collection",
      "href": "../collection.json",
      "type": "application/json",
      "title": "scalloped_depression"
    },
    {
      "rel": "parent",
      "href": "../collection.json",
      "type": "application/json",
      "title": "scalloped_depression"
    }
  ],
  "assets": {},
  "collection": "ias_scalloped_depression"
}