{
  "type": "Feature",
  "stac_version": "1.1.0",
  "stac_extensions": [
    "https://stac-extensions.github.io/ssys/v1.1.0/schema.json"
  ],
  "id": "6633",
  "geometry": {
    "type": "MultiPolygon",
    "coordinates": [
      [
        [
          [
            88.88070627479514,
            43.86467008727884,
            0.0
          ],
          [
            88.87632167100617,
            43.86467008727885,
            0.0
          ],
          [
            88.88133264676509,
            43.85777999561027,
            0.0
          ],
          [
            88.88227220471992,
            43.85746680962541,
            0.0
          ],
          [
            88.88759636646392,
            43.8587195535651,
            0.0
          ],
          [
            88.88070627479514,
            43.86467008727884,
            0.0
          ]
        ]
      ]
    ]
  },
  "bbox": [
    88.87632167100617,
    43.85746680962541,
    88.88759636646392,
    43.86467008727885
  ],
  "properties": {
    "Name": "0",
    "description": null,
    "begin": null,
    "end": null,
    "altitudeMode": null,
    "tessellate": -1,
    "extrude": 0,
    "visibility": -1,
    "ssys:targets": [
      "mars"
    ],
    "ssys:local_time": null,
    "ssys:target_class": "planet",
    "instruments": [
      "hirise"
    ],
    "platform": "mro",
    "datetime": "2011-05-11T00:00:00Z"
  },
  "links": [
    {
      "rel": "root",
      "href": "../../../catalog.json",
      "type": "application/json"
    },
    {
      "rel": "collection",
      "href": "../collection.json",
      "type": "application/json",
      "title": "scalloped_depression"
    },
    {
      "rel": "parent",
      "href": "../collection.json",
      "type": "application/json",
      "title": "scalloped_depression"
    }
  ],
  "assets": {},
  "collection": "ias_scalloped_depression"
}