{
  "type": "Feature",
  "stac_version": "1.1.0",
  "stac_extensions": [
    "https://stac-extensions.github.io/ssys/v1.1.0/schema.json"
  ],
  "id": "12302",
  "geometry": {
    "type": "Polygon",
    "coordinates": [
      [
        [
          142.72519954389963,
          -31.151653363739968
        ],
        [
          142.54173496294186,
          -31.132934987884767
        ],
        [
          142.60153132126584,
          -31.0485853762828
        ],
        [
          142.55202394526816,
          -31.026493015963524
        ],
        [
          142.60097455815287,
          -30.984301507269095
        ],
        [
          142.5987920467503,
          -30.957020114737702
        ],
        [
          142.64622826396817,
          -30.935851981185863
        ],
        [
          142.68553573973782,
          -30.890241946978335
        ],
        [
          142.7830583665908,
          -30.911354404218855
        ],
        [
          142.87258587514248,
          -30.935851981185863
        ],
        [
          143.01110853762827,
          -30.95696443842644
        ],
        [
          143.0550260119726,
          -30.98146201539339
        ],
        [
          143.21466113169902,
          -31.00579256342644
        ],
        [
          143.19354867445838,
          -31.027072049600918
        ],
        [
          143.05005968500586,
          -31.048941704674974
        ],
        [
          142.7845282212087,
          -31.09736896023378
        ],
        [
          142.73575577252006,
          -31.13940457525655
        ],
        [
          142.72519954389963,
          -31.151653363739968
        ]
      ],
      [
        [
          142.65678449258837,
          -31.037628278221177
        ],
        [
          142.62899087799326,
          -31.04543409706389
        ],
        [
          142.64896753848348,
          -31.065433028078644
        ],
        [
          142.65678449258837,
          -31.037628278221177
        ],
        [
          142.8015874429875,
          -31.02704977907638
        ],
        [
          142.8164196123148,
          -30.969213226909915
        ],
        [
          142.84421322691003,
          -30.96140740806726
        ],
        [
          142.8242365664196,
          -30.94140847705245
        ],
        [
          142.8164196123148,
          -30.969213226909915
        ],
        [
          142.77659991448127,
          -30.975014698546147
        ],
        [
          142.74221422462938,
          -31.009021789481153
        ],
        [
          142.66257482896242,
          -31.02062473275373
        ],
        [
          142.65678449258837,
          -31.037628278221177
        ]
      ],
      [
        [
          142.8620296465225,
          -31.06043329532497
        ],
        [
          142.84964723489168,
          -31.031481613454957
        ],
        [
          142.8095825612885,
          -31.051191027651043
        ],
        [
          142.8620296465225,
          -31.06043329532497
        ]
      ]
    ]
  },
  "bbox": [
    142.54173496294186,
    -31.151653363739968,
    143.21466113169902,
    -30.890241946978335
  ],
  "properties": {
    "grid_code": 255,
    "Shape_Leng": 2.309626,
    "Shape_Area": 0.080906,
    "ssys:targets": [
      "mars"
    ],
    "ssys:local_time": null,
    "ssys:target_class": "planet",
    "instruments": [
      "crism",
      "omega"
    ],
    "platform": "mro/mex",
    "gsd": 0.3,
    "datetime": "2013-04-24T00:00:00Z"
  },
  "links": [
    {
      "rel": "root",
      "href": "../../../catalog.json",
      "type": "application/json"
    },
    {
      "rel": "collection",
      "href": "../collection.json",
      "type": "application/json",
      "title": "hyd_global_290615"
    },
    {
      "rel": "parent",
      "href": "../collection.json",
      "type": "application/json",
      "title": "hyd_global_290615"
    }
  ],
  "assets": {},
  "collection": "ias_hyd_global_290615"
}