{
  "type": "Feature",
  "stac_version": "1.1.0",
  "stac_extensions": [
    "https://stac-extensions.github.io/ssys/v1.1.1/schema.json"
  ],
  "id": "2068",
  "geometry": {
    "type": "MultiPolygon",
    "coordinates": [
      [
        [
          [
            98.75812324206247,
            43.64733188542714,
            0.0
          ],
          [
            98.75794497684227,
            43.6466633908512,
            0.0
          ],
          [
            98.75830150728285,
            43.64572749844496,
            0.0
          ],
          [
            98.75986132795991,
            43.64537096800439,
            0.0
          ],
          [
            98.76088635297639,
            43.64630686041062,
            0.0
          ],
          [
            98.76079722036631,
            43.64737645173227,
            0.0
          ],
          [
            98.75812324206247,
            43.64733188542714,
            0.0
          ]
        ]
      ]
    ]
  },
  "bbox": [
    98.75794497684227,
    43.64537096800439,
    98.76088635297639,
    43.64737645173227
  ],
  "properties": {
    "Name": "0",
    "description": null,
    "begin": null,
    "end": null,
    "altitudeMode": null,
    "tessellate": -1,
    "extrude": 0,
    "visibility": -1,
    "ssys:targets": [
      "mars"
    ],
    "ssys:local_time": "",
    "ssys:target_class": "planet",
    "instruments": [
      "hirise"
    ],
    "platform": "mro",
    "datetime": "2011-05-11T00:00:00Z"
  },
  "links": [
    {
      "rel": "root",
      "href": "../../../catalog.json",
      "type": "application/json"
    },
    {
      "rel": "collection",
      "href": "../collection.json",
      "type": "application/json",
      "title": "scalloped_depression"
    },
    {
      "rel": "parent",
      "href": "../collection.json",
      "type": "application/json",
      "title": "scalloped_depression"
    }
  ],
  "assets": {},
  "collection": "ias_scalloped_depression"
}