{
  "type": "Feature",
  "stac_version": "1.1.0",
  "stac_extensions": [
    "https://stac-extensions.github.io/ssys/v1.1.0/schema.json"
  ],
  "id": "2264",
  "geometry": {
    "type": "MultiPolygon",
    "coordinates": [
      [
        [
          [
            98.5764696235372,
            45.04804219541479,
            0.0
          ],
          [
            98.57654885252252,
            45.04606147078233,
            0.0
          ],
          [
            98.57765805831677,
            45.04471457803209,
            0.0
          ],
          [
            98.57979724091996,
            45.04384305919383,
            0.0
          ],
          [
            98.58328331627331,
            45.04257539542896,
            0.0
          ],
          [
            98.5842340640969,
            45.04352614325252,
            0.0
          ],
          [
            98.58661093365582,
            45.04400151716448,
            0.0
          ],
          [
            98.58922549017073,
            45.04558609687035,
            0.0
          ],
          [
            98.5877993684354,
            45.04875525628258,
            0.0
          ],
          [
            98.58589787278822,
            45.05026060700312,
            0.0
          ],
          [
            98.58367946119976,
            45.05081520990024,
            0.0
          ],
          [
            98.5799556988906,
            45.05089443888557,
            0.0
          ],
          [
            98.57734114237563,
            45.04978523309131,
            0.0
          ],
          [
            98.5764696235372,
            45.04804219541479,
            0.0
          ]
        ]
      ]
    ]
  },
  "bbox": [
    98.5764696235372,
    45.04257539542896,
    98.58922549017073,
    45.05089443888557
  ],
  "properties": {
    "Name": "0",
    "description": null,
    "begin": null,
    "end": null,
    "altitudeMode": null,
    "tessellate": -1,
    "extrude": 0,
    "visibility": -1,
    "ssys:targets": [
      "mars"
    ],
    "ssys:local_time": "",
    "ssys:target_class": "planet",
    "instruments": [
      "hirise"
    ],
    "platform": "mro",
    "datetime": "2011-05-11T00:00:00Z"
  },
  "links": [
    {
      "rel": "root",
      "href": "../../../catalog.json",
      "type": "application/json"
    },
    {
      "rel": "collection",
      "href": "../collection.json",
      "type": "application/json",
      "title": "scalloped_depression"
    },
    {
      "rel": "parent",
      "href": "../collection.json",
      "type": "application/json",
      "title": "scalloped_depression"
    }
  ],
  "assets": {},
  "collection": "ias_scalloped_depression"
}