{
  "type": "Feature",
  "stac_version": "1.1.0",
  "stac_extensions": [
    "https://stac-extensions.github.io/ssys/v1.1.1/schema.json"
  ],
  "id": "3899",
  "geometry": {
    "type": "MultiPolygon",
    "coordinates": [
      [
        [
          [
            84.3606265152265,
            44.45397935936621,
            0.0
          ],
          [
            84.31928549223619,
            44.44606299326166,
            0.0
          ],
          [
            84.29113841275334,
            44.44694258949555,
            0.0
          ],
          [
            84.26387092950425,
            44.45441915748324,
            0.0
          ],
          [
            84.22692788768317,
            44.47904785203064,
            0.0
          ],
          [
            84.20405838560337,
            44.51027351833199,
            0.0
          ],
          [
            84.18470726845895,
            44.5225878656056,
            0.0
          ],
          [
            84.17986948917279,
            44.53006443359328,
            0.0
          ],
          [
            84.16315716072988,
            44.53006443359329,
            0.0
          ],
          [
            84.15128261157298,
            44.52918483735937,
            0.0
          ],
          [
            84.13808866806544,
            44.52214806748877,
            0.0
          ],
          [
            84.13061210007778,
            44.52082867313801,
            0.0
          ],
          [
            84.12137633962254,
            44.51906948067024,
            0.0
          ],
          [
            84.12841310949312,
            44.47201108216001,
            0.0
          ],
          [
            84.15875917956059,
            44.46673350475685,
            0.0
          ],
          [
            84.17371231553591,
            44.46013653300309,
            0.0
          ],
          [
            84.18514706657582,
            44.46629370663999,
            0.0
          ],
          [
            84.19482262514794,
            44.46365491793846,
            0.0
          ],
          [
            84.19702161573257,
            44.45705794618471,
            0.0
          ],
          [
            84.18470726845895,
            44.45485895560007,
            0.0
          ],
          [
            84.18294807599118,
            44.45178036878173,
            0.0
          ],
          [
            84.19042464397882,
            44.44166501209259,
            0.0
          ],
          [
            84.20185939501873,
            44.43330884787099,
            0.0
          ],
          [
            84.21065535735714,
            44.42539248176649,
            0.0
          ],
          [
            84.22384930086463,
            44.42187409683112,
            0.0
          ],
          [
            84.23836263872293,
            44.41659651942808,
            0.0
          ],
          [
            84.25155658223058,
            44.41615672131126,
            0.0
          ],
          [
            84.26343113138738,
            44.42187409683111,
            0.0
          ],
          [
            84.27618527677804,
            44.42187409683112,
            0.0
          ],
          [
            84.29289760522094,
            44.41923530812961,
            0.0
          ],
          [
            84.30521195249473,
            44.42583227988337,
            0.0
          ],
          [
            84.31796609788539,
            44.42275369306498,
            0.0
          ],
          [
            84.32984064704219,
            44.41879551001272,
            0.0
          ],
          [
            84.34875196606974,
            44.42319349118186,
            0.0
          ],
          [
            84.35798772652497,
            44.42583227988338,
            0.0
          ],
          [
            84.36546429451265,
            44.43110985728633,
            0.0
          ],
          [
            84.36986227568195,
            44.44430380079405,
            0.0
          ],
          [
            84.3606265152265,
            44.45397935936621,
            0.0
          ]
        ]
      ]
    ]
  },
  "bbox": [
    84.12137633962254,
    44.41615672131126,
    84.36986227568195,
    44.53006443359329
  ],
  "properties": {
    "Name": "0",
    "description": null,
    "begin": null,
    "end": null,
    "altitudeMode": null,
    "tessellate": -1,
    "extrude": 0,
    "visibility": -1,
    "ssys:targets": [
      "mars"
    ],
    "ssys:local_time": "",
    "ssys:target_class": "planet",
    "instruments": [
      "hirise"
    ],
    "platform": "mro",
    "datetime": "2011-05-11T00:00:00Z"
  },
  "links": [
    {
      "rel": "root",
      "href": "../../../catalog.json",
      "type": "application/json"
    },
    {
      "rel": "collection",
      "href": "../collection.json",
      "type": "application/json",
      "title": "scalloped_depression"
    },
    {
      "rel": "parent",
      "href": "../collection.json",
      "type": "application/json",
      "title": "scalloped_depression"
    }
  ],
  "assets": {},
  "collection": "ias_scalloped_depression"
}