{
  "type": "Feature",
  "stac_version": "1.1.0",
  "stac_extensions": [
    "https://stac-extensions.github.io/ssys/v1.1.1/schema.json"
  ],
  "id": "7478",
  "geometry": {
    "type": "MultiPolygon",
    "coordinates": [
      [
        [
          [
            90.02818673681195,
            46.6281689930708,
            0.0
          ],
          [
            90.03996294527876,
            46.62300863205708,
            0.0
          ],
          [
            90.0453879401906,
            46.62591960493655,
            0.0
          ],
          [
            90.04856354696828,
            46.62658118968193,
            0.0
          ],
          [
            90.05147451984777,
            46.63068301510294,
            0.0
          ],
          [
            90.05081293510239,
            46.63174155069562,
            0.0
          ],
          [
            90.04485867239441,
            46.63015374730674,
            0.0
          ],
          [
            90.03837514189013,
            46.62962447951043,
            0.0
          ],
          [
            90.03070075884426,
            46.63372630493159,
            0.0
          ],
          [
            90.02977454020076,
            46.63557874221858,
            0.0
          ],
          [
            90.0222324741038,
            46.63491715747318,
            0.0
          ],
          [
            90.02315869274729,
            46.63147691679735,
            0.0
          ],
          [
            90.02818673681195,
            46.6281689930708,
            0.0
          ]
        ]
      ]
    ]
  },
  "bbox": [
    90.0222324741038,
    46.62300863205708,
    90.05147451984777,
    46.63557874221858
  ],
  "properties": {
    "Name": "0",
    "description": null,
    "begin": null,
    "end": null,
    "altitudeMode": null,
    "tessellate": -1,
    "extrude": 0,
    "visibility": -1,
    "ssys:targets": [
      "mars"
    ],
    "ssys:local_time": "",
    "ssys:target_class": "planet",
    "instruments": [
      "hirise"
    ],
    "platform": "mro",
    "datetime": "2011-05-11T00:00:00Z"
  },
  "links": [
    {
      "rel": "root",
      "href": "../../../catalog.json",
      "type": "application/json"
    },
    {
      "rel": "collection",
      "href": "../collection.json",
      "type": "application/json",
      "title": "scalloped_depression"
    },
    {
      "rel": "parent",
      "href": "../collection.json",
      "type": "application/json",
      "title": "scalloped_depression"
    }
  ],
  "assets": {},
  "collection": "ias_scalloped_depression"
}