{
  "type": "Feature",
  "stac_version": "1.1.0",
  "stac_extensions": [
    "https://stac-extensions.github.io/ssys/v1.1.0/schema.json"
  ],
  "id": "539",
  "geometry": {
    "type": "MultiPolygon",
    "coordinates": [
      [
        [
          [
            91.43125297193187,
            44.98666282016075,
            0.0
          ],
          [
            91.43118774971956,
            44.9854235981266,
            0.0
          ],
          [
            91.43190519405532,
            44.98470615379104,
            0.0
          ],
          [
            91.43203563847997,
            44.98353215396903,
            0.0
          ],
          [
            91.43320963830182,
            44.98314082069516,
            0.0
          ],
          [
            91.43405752706205,
            44.98216248751021,
            0.0
          ],
          [
            91.43536197130872,
            44.98072759883905,
            0.0
          ],
          [
            91.43855785971274,
            44.97974926565411,
            0.0
          ],
          [
            91.44201463696601,
            44.97948837680473,
            0.0
          ],
          [
            91.44508008094554,
            44.98014059892797,
            0.0
          ],
          [
            91.44527574758241,
            44.98131459874993,
            0.0
          ],
          [
            91.44710196952762,
            44.98294515405815,
            0.0
          ],
          [
            91.44905863589752,
            44.98255382078407,
            0.0
          ],
          [
            91.45127619111668,
            44.98183637644849,
            0.0
          ],
          [
            91.45192841323988,
            44.98222770972257,
            0.0
          ],
          [
            91.45303719084954,
            44.98151026538699,
            0.0
          ],
          [
            91.45492863500708,
            44.98131459874993,
            0.0
          ],
          [
            91.45571130155501,
            44.98314082069516,
            0.0
          ],
          [
            91.45695052358917,
            44.98333648733216,
            0.0
          ],
          [
            91.45845063447284,
            44.98314082069515,
            0.0
          ],
          [
            91.46001596756872,
            44.98359737618138,
            0.0
          ],
          [
            91.46047252305492,
            44.98483659821569,
            0.0
          ],
          [
            91.46158130066459,
            44.98509748706486,
            0.0
          ],
          [
            91.46197263393842,
            44.98594537582518,
            0.0
          ],
          [
            91.46229874500017,
            44.98744548670869,
            0.0
          ],
          [
            91.45929852323297,
            44.98809770883207,
            0.0
          ],
          [
            91.45903763438378,
            44.98594537582517,
            0.0
          ],
          [
            91.45779841234945,
            44.98516270927722,
            0.0
          ],
          [
            91.45655919031532,
            44.98529315370188,
            0.0
          ],
          [
            91.4553851904933,
            44.98627148688689,
            0.0
          ],
          [
            91.45499385721943,
            44.98535837591425,
            0.0
          ],
          [
            91.45329807969892,
            44.98698893122247,
            0.0
          ],
          [
            91.45179796881541,
            44.98535837591425,
            0.0
          ],
          [
            91.44886296926052,
            44.98607582024982,
            0.0
          ],
          [
            91.45049352456873,
            44.98751070892104,
            0.0
          ],
          [
            91.44912385810987,
            44.98842381989363,
            0.0
          ],
          [
            91.44644974740442,
            44.98777159777041,
            0.0
          ],
          [
            91.44449308103454,
            44.98614104246217,
            0.0
          ],
          [
            91.44247119245243,
            44.98653237573603,
            0.0
          ],
          [
            91.44214508139072,
            44.9863367090992,
            0.0
          ],
          [
            91.43992752617162,
            44.98685848679777,
            0.0
          ],
          [
            91.43666641555522,
            44.98685848679776,
            0.0
          ],
          [
            91.43431841591142,
            44.98653237573603,
            0.0
          ],
          [
            91.43288352724026,
            44.98731504228415,
            0.0
          ],
          [
            91.43125297193187,
            44.98666282016075,
            0.0
          ]
        ]
      ]
    ]
  },
  "bbox": [
    91.43118774971956,
    44.97948837680473,
    91.46229874500017,
    44.98842381989363
  ],
  "properties": {
    "Name": "0",
    "description": null,
    "begin": null,
    "end": null,
    "altitudeMode": null,
    "tessellate": -1,
    "extrude": 0,
    "visibility": -1,
    "ssys:targets": [
      "mars"
    ],
    "ssys:local_time": "",
    "ssys:target_class": "planet",
    "instruments": [
      "hirise"
    ],
    "platform": "mro",
    "datetime": "2011-05-11T00:00:00Z"
  },
  "links": [
    {
      "rel": "root",
      "href": "../../../catalog.json",
      "type": "application/json"
    },
    {
      "rel": "collection",
      "href": "../collection.json",
      "type": "application/json",
      "title": "scalloped_depression"
    },
    {
      "rel": "parent",
      "href": "../collection.json",
      "type": "application/json",
      "title": "scalloped_depression"
    }
  ],
  "assets": {},
  "collection": "ias_scalloped_depression"
}