{
  "type": "Feature",
  "stac_version": "1.1.0",
  "stac_extensions": [
    "https://stac-extensions.github.io/ssys/v1.1.0/schema.json"
  ],
  "id": "3409",
  "geometry": {
    "type": "MultiPolygon",
    "coordinates": [
      [
        [
          [
            98.68877303257949,
            46.47982010274519,
            0.0
          ],
          [
            98.67803794649647,
            46.4781427455447,
            0.0
          ],
          [
            98.66914795333388,
            46.48065878134553,
            0.0
          ],
          [
            98.66159984593185,
            46.48082651706541,
            0.0
          ],
          [
            98.66176758165193,
            46.47545897402392,
            0.0
          ],
          [
            98.66294173169223,
            46.46975595954246,
            0.0
          ],
          [
            98.66713512469337,
            46.46975595954247,
            0.0
          ],
          [
            98.67418002493541,
            46.47394935254364,
            0.0
          ],
          [
            98.67652832501601,
            46.47260746678307,
            0.0
          ],
          [
            98.6773670036162,
            46.46925275238226,
            0.0
          ],
          [
            98.67904436081669,
            46.46774313090181,
            0.0
          ],
          [
            98.68122492517728,
            46.46774313090181,
            0.0
          ],
          [
            98.68390869669804,
            46.46791086662187,
            0.0
          ],
          [
            98.68592152533869,
            46.47042690242256,
            0.0
          ],
          [
            98.68927623973968,
            46.47596218118411,
            0.0
          ],
          [
            98.68877303257949,
            46.47982010274519,
            0.0
          ]
        ]
      ]
    ]
  },
  "bbox": [
    98.66159984593185,
    46.46774313090181,
    98.68927623973968,
    46.48082651706541
  ],
  "properties": {
    "Name": "0",
    "description": null,
    "begin": null,
    "end": null,
    "altitudeMode": null,
    "tessellate": -1,
    "extrude": 0,
    "visibility": -1,
    "ssys:targets": [
      "mars"
    ],
    "ssys:local_time": null,
    "ssys:target_class": "planet",
    "instruments": [
      "hirise"
    ],
    "platform": "mro",
    "datetime": "2011-05-11T00:00:00Z"
  },
  "links": [
    {
      "rel": "root",
      "href": "../../../catalog.json",
      "type": "application/json"
    },
    {
      "rel": "collection",
      "href": "../collection.json",
      "type": "application/json",
      "title": "scalloped_depression"
    },
    {
      "rel": "parent",
      "href": "../collection.json",
      "type": "application/json",
      "title": "scalloped_depression"
    }
  ],
  "assets": {},
  "collection": "ias_scalloped_depression"
}