{
  "type": "Feature",
  "stac_version": "1.1.0",
  "stac_extensions": [
    "https://stac-extensions.github.io/ssys/v1.1.0/schema.json"
  ],
  "id": "62",
  "geometry": {
    "type": "MultiPolygon",
    "coordinates": [
      [
        [
          [
            92.20083259135976,
            44.37654998773417,
            0.0
          ],
          [
            92.1990737803038,
            44.37540676054777,
            0.0
          ],
          [
            92.199865245279,
            44.37356000893908,
            0.0
          ],
          [
            92.2017119968877,
            44.37268060341114,
            0.0
          ],
          [
            92.2039105107076,
            44.37312030617511,
            0.0
          ],
          [
            92.20505373789392,
            44.37250472230557,
            0.0
          ],
          [
            92.20646078673866,
            44.37320824672793,
            0.0
          ],
          [
            92.21015428995604,
            44.37241678175275,
            0.0
          ],
          [
            92.2145513175958,
            44.37338412783351,
            0.0
          ],
          [
            92.21472719870142,
            44.37461529557265,
            0.0
          ],
          [
            92.21771717749645,
            44.37725351215654,
            0.0
          ],
          [
            92.21718953417967,
            44.37918820431798,
            0.0
          ],
          [
            92.21428749593744,
            44.37927614487082,
            0.0
          ],
          [
            92.21024223050885,
            44.37848467989564,
            0.0
          ],
          [
            92.20874724111133,
            44.37830879879006,
            0.0
          ],
          [
            92.20725225171384,
            44.37628616607578,
            0.0
          ],
          [
            92.20083259135976,
            44.37654998773417,
            0.0
          ]
        ]
      ]
    ]
  },
  "bbox": [
    92.1990737803038,
    44.37241678175275,
    92.21771717749645,
    44.37927614487082
  ],
  "properties": {
    "Name": "0",
    "description": null,
    "begin": null,
    "end": null,
    "altitudeMode": null,
    "tessellate": -1,
    "extrude": 0,
    "visibility": -1,
    "ssys:targets": [
      "mars"
    ],
    "ssys:local_time": "",
    "ssys:target_class": "planet",
    "instruments": [
      "hirise"
    ],
    "platform": "mro",
    "datetime": "2011-05-11T00:00:00Z"
  },
  "links": [
    {
      "rel": "root",
      "href": "../../../catalog.json",
      "type": "application/json"
    },
    {
      "rel": "collection",
      "href": "../collection.json",
      "type": "application/json",
      "title": "scalloped_depression"
    },
    {
      "rel": "parent",
      "href": "../collection.json",
      "type": "application/json",
      "title": "scalloped_depression"
    }
  ],
  "assets": {},
  "collection": "ias_scalloped_depression"
}