{
  "type": "Feature",
  "stac_version": "1.1.0",
  "stac_extensions": [
    "https://stac-extensions.github.io/ssys/v1.1.0/schema.json"
  ],
  "id": "9146",
  "geometry": {
    "type": "MultiPolygon",
    "coordinates": [
      [
        [
          [
            100.7643133154834,
            48.91354007711056,
            0.0
          ],
          [
            100.7414195402782,
            48.91424450096292,
            0.0
          ],
          [
            100.7224000962615,
            48.90226929547099,
            0.0
          ],
          [
            100.7449416595404,
            48.88395427530673,
            0.0
          ],
          [
            100.7755840971229,
            48.90156487161841,
            0.0
          ],
          [
            100.796716812697,
            48.91142680555318,
            0.0
          ],
          [
            100.8044654750741,
            48.90508699088083,
            0.0
          ],
          [
            100.8160884686398,
            48.89099851383146,
            0.0
          ],
          [
            100.8248937667957,
            48.89205514961014,
            0.0
          ],
          [
            100.8347557007302,
            48.89592948079883,
            0.0
          ],
          [
            100.8456742704434,
            48.90403035510212,
            0.0
          ],
          [
            100.8558884163043,
            48.9226975871925,
            0.0
          ],
          [
            100.868920257575,
            48.93009403764359,
            0.0
          ],
          [
            100.8886441254441,
            48.93432058075837,
            0.0
          ],
          [
            100.9256263776988,
            48.92974182571726,
            0.0
          ],
          [
            100.9552121795024,
            48.9272763422336,
            0.0
          ],
          [
            100.9608475703222,
            48.96284974678332,
            0.0
          ],
          [
            100.9513378483139,
            48.99173112473456,
            0.0
          ],
          [
            100.9287962850349,
            49.00018421096428,
            0.0
          ],
          [
            100.9002671190099,
            48.99419660821827,
            0.0
          ],
          [
            100.8756122841734,
            48.97658601190654,
            0.0
          ],
          [
            100.8210194356072,
            48.94136481928307,
            0.0
          ],
          [
            100.7643133154834,
            48.91354007711056,
            0.0
          ]
        ]
      ]
    ]
  },
  "bbox": [
    100.7224000962615,
    48.88395427530673,
    100.9608475703222,
    49.00018421096428
  ],
  "properties": {
    "Name": "0",
    "description": null,
    "begin": null,
    "end": null,
    "altitudeMode": null,
    "tessellate": -1,
    "extrude": 0,
    "visibility": -1,
    "ssys:targets": [
      "mars"
    ],
    "ssys:local_time": null,
    "ssys:target_class": "planet",
    "instruments": [
      "hirise"
    ],
    "platform": "mro",
    "datetime": "2011-05-11T00:00:00Z"
  },
  "links": [
    {
      "rel": "root",
      "href": "../../../catalog.json",
      "type": "application/json"
    },
    {
      "rel": "collection",
      "href": "../collection.json",
      "type": "application/json",
      "title": "scalloped_depression"
    },
    {
      "rel": "parent",
      "href": "../collection.json",
      "type": "application/json",
      "title": "scalloped_depression"
    }
  ],
  "assets": {},
  "collection": "ias_scalloped_depression"
}