{
  "type": "Feature",
  "stac_version": "1.1.0",
  "stac_extensions": [
    "https://stac-extensions.github.io/ssys/v1.1.0/schema.json"
  ],
  "id": "10887",
  "geometry": {
    "type": "Polygon",
    "coordinates": [
      [
        [
          -61.99543899657914,
          -23.033067274800487
        ],
        [
          -62.02508106470924,
          -23.020384211088924
        ],
        [
          -62.00456991163048,
          -22.981243764253122
        ],
        [
          -61.99543899657914,
          -23.033067274800487
        ]
      ]
    ]
  },
  "bbox": [
    -62.02508106470924,
    -23.033067274800487,
    -61.99543899657914,
    -22.981243764253122
  ],
  "properties": {
    "grid_code": 255,
    "Shape_Leng": 0.129052,
    "Shape_Area": 0.00071,
    "ssys:targets": [
      "mars"
    ],
    "ssys:local_time": "",
    "ssys:target_class": "planet",
    "instruments": [
      "crism",
      "omega"
    ],
    "platform": "mro/mex",
    "gsd": 0.3,
    "datetime": "2013-04-24T00:00:00Z"
  },
  "links": [
    {
      "rel": "root",
      "href": "../../../catalog.json",
      "type": "application/json"
    },
    {
      "rel": "collection",
      "href": "../collection.json",
      "type": "application/json",
      "title": "hyd_global_290615"
    },
    {
      "rel": "parent",
      "href": "../collection.json",
      "type": "application/json",
      "title": "hyd_global_290615"
    }
  ],
  "assets": {},
  "collection": "ias_hyd_global_290615"
}