{
  "type": "Feature",
  "stac_version": "1.1.0",
  "stac_extensions": [
    "https://stac-extensions.github.io/ssys/v1.1.0/schema.json"
  ],
  "id": "6397",
  "geometry": {
    "type": "MultiPolygon",
    "coordinates": [
      [
        [
          [
            88.06516980634005,
            44.61277610192121,
            0.0
          ],
          [
            88.0564968457171,
            44.61312302034605,
            0.0
          ],
          [
            88.05372149831759,
            44.61138842822152,
            0.0
          ],
          [
            88.06308829579052,
            44.60583773342262,
            0.0
          ],
          [
            88.06690439846471,
            44.60653157027248,
            0.0
          ],
          [
            88.06759823531456,
            44.60965383609683,
            0.0
          ],
          [
            88.06516980634005,
            44.61277610192121,
            0.0
          ]
        ]
      ]
    ]
  },
  "bbox": [
    88.05372149831759,
    44.60583773342262,
    88.06759823531456,
    44.61312302034605
  ],
  "properties": {
    "Name": "0",
    "description": null,
    "begin": null,
    "end": null,
    "altitudeMode": null,
    "tessellate": -1,
    "extrude": 0,
    "visibility": -1,
    "ssys:targets": [
      "mars"
    ],
    "ssys:local_time": "",
    "ssys:target_class": "planet",
    "instruments": [
      "hirise"
    ],
    "platform": "mro",
    "datetime": "2011-05-11T00:00:00Z"
  },
  "links": [
    {
      "rel": "root",
      "href": "../../../catalog.json",
      "type": "application/json"
    },
    {
      "rel": "collection",
      "href": "../collection.json",
      "type": "application/json",
      "title": "scalloped_depression"
    },
    {
      "rel": "parent",
      "href": "../collection.json",
      "type": "application/json",
      "title": "scalloped_depression"
    }
  ],
  "assets": {},
  "collection": "ias_scalloped_depression"
}